lab1/alu/alu.v
`include "alu_func.v"

module alu #(parameter data_width = 16) (
	input [data_width - 1 : 0] A, 
	input [data_width - 1 : 0] B, 
	input [3 : 0] FuncCode,
       	output reg [data_width - 1: 0] C,
       	output reg OverflowFlag);
// Do not use delay in your implementation.

// You can declare any variables as needed.
/*
	YOUR VARIABLE DECLARATION...
*/

initial begin
	C = 0;
	OverflowFlag = 0;
end   	

// TODO: You should implement the functionality of ALU!
// (HINT: Use 'always @(...) begin ... end')
/*
	YOUR ALU FUNCTIONALITY IMPLEMENTATION...
*/
	always begin
		case (FuncCode)
			`FUNC_ADD: begin
				assign C = A + B;
				assign OverflowFlag = ~(A[data_width - 1] ^ B[data_width - 1]) & (A[data_width - 1] ^ C[data_width - 1]);
			end
			`FUNC_SUB: begin
				assign C = A - B;
				assign OverflowFlag = (A[data_width - 1] ^ B[data_width - 1]) & (A[data_width - 1] ^ C[data_width - 1]);
			end
			`FUNC_ID: begin
				assign C = A;
				assign OverflowFlag = 1'b0;
			end
			`FUNC_NOT: begin
				assign C = ~A;
				assign OverflowFlag = 1'b0;
			end
			`FUNC_AND: begin
				assign C = A & B;
				assign OverflowFlag = 1'b0;
			end
			`FUNC_OR: begin
				assign C = A | B;
				assign OverflowFlag = 1'b0;
			end
			`FUNC_NAND: begin
				assign C = ~(A & B);
				assign OverflowFlag = 1'b0;
			end
			`FUNC_NOR: begin
				assign C = ~(A | B);
				assign OverflowFlag = 1'b0;
			end
			`FUNC_XOR: begin
				assign C = A ^ B;
				assign OverflowFlag = 1'b0;
			end
			`FUNC_XNOR: begin
				assign C = ~(A ^ B);
				assign OverflowFlag = 1'b0;
			end
			`FUNC_LLS: begin
				assign C = A << 1;
				assign OverflowFlag = 1'b0;
			end
			`FUNC_LRS: begin
				assign C = A >> 1;
				assign OverflowFlag = 1'b0;
			end
			`FUNC_ALS: begin
				assign C = signed'(A) <<< 1;
				assign OverflowFlag = 1'b0;
			end
			`FUNC_ARS: begin
				assign C = signed'(A) >>> 1;
				assign OverflowFlag = 1'b0;
			end
			`FUNC_TCP: begin
				assign C = ~A + 1;
				assign OverflowFlag = 1'b0;
			end
			`FUNC_ZERO: begin
				assign C = 16'b0000_0000_0000_0000;
				assign OverflowFlag = 1'b0;
			end
		endcase
	end

endmodule

lab1/alu/waveform.vcd
$version Generated by VerilatedVcd $end
$timescale 1ps $end
 $scope module TOP $end
  $var wire 16 # A [15:0] $end
  $var wire 16 $ B [15:0] $end
  $var wire 4 % FuncCode [3:0] $end
  $var wire 16 & C [15:0] $end
  $var wire 1 ' OverflowFlag $end
  $scope module alu $end
   $var wire 32 ( data_width [31:0] $end
   $var wire 16 # A [15:0] $end
   $var wire 16 $ B [15:0] $end
   $var wire 4 % FuncCode [3:0] $end
   $var wire 16 & C [15:0] $end
   $var wire 1 ' OverflowFlag $end
  $upscope $end
 $upscope $end
$enddefinitions $end


#0
b0000000000000001 #
b0000000000000001 $
b0000 %
b0000000000000010 &
0'
b00000000000000000000000000010000 (
#1
#2
b1111111111111111 #
b0000000000000000 &
#3
#4
b0111111111111111 #
b0000000000000101 $
b1000000000000100 &
1'
#5
#6
b1000000000000000 #
b1000000000000001 $
b0000000000000001 &
#7
#8
b0000111111111111 #
b0000000000000001 $
b0001000000000000 &
0'
#9
#10
b0111111111111111 #
b1000000000000000 &
1'
#11
#12
b0000000000000000 #
b0000000000000000 $
b0001 %
b0000000000000000 &
0'
#13
#14
b0000000000000011 #
b0000000000000001 $
b0000000000000010 &
#15
#16
b1111111111111111 #
b1000000000000001 $
b0111111111111110 &
#17
#18
b0111111111111111 #
b1111111111111111 $
b1000000000000000 &
1'
#19
#20
b0000000000000010 #
b0000000000000011 $
b1111111111111111 &
0'
#21
#22
b0000000000000000 #
b0000000000000000 $
b0010 %
b0000000000000000 &
#23
#24
b0000000000001010 #
b0000000000001010 &
#25
#26
b1111111111111111 #
b0011 %
b0000000000000000 &
#27
#28
b0000000000000000 #
b1111111111111111 &
#29
#30
b0000000000000100 #
b0100 %
b0000000000000000 &
#31
#32
b0000000000000001 #
b0000000000000010 $
#33
#34
b0011001100110011 #
b0101010101010101 $
b0101 %
b0111011101110111 &
#35
#36
b1100110011001100 #
b1101110111011101 &
#37
#38
b0011001100110011 #
b0110 %
b1110111011101110 &
#39
#40
b1100110011001100 #
b1011101110111011 &
#41
#42
b0011001100110011 #
b0111 %
b1000100010001000 &
#43
#44
b1100110011001100 #
b0010001000100010 &
#45
#46
b0011001100110011 #
b1000 %
b0110011001100110 &
#47
#48
b1100110011001100 #
b1001100110011001 &
#49
#50
b0011001100110011 #
b1001 %
#51
#52
b1100110011001100 #
b0110011001100110 &
#53
#54
b0000100000000000 #
b0000000000000000 $
b1010 %
b0001000000000000 &
#55
#56
b1000000000000000 #
b0000000000000000 &
#57
#58
b0000100000000000 #
b1011 %
b0000010000000000 &
#59
#60
b1000000000000000 #
b0100000000000000 &
#61
#62
b1111000000000001 #
b0111100000000000 &
#63
#64
b0000100000000000 #
b1100 %
b0001000000000000 &
#65
#66
b1000000000000000 #
b0000000000000000 &
#67
#68
b0000100000000000 #
b1101 %
b0000010000000000 &
#69
#70
b1000000000000000 #
b1100000000000000 &
#71
#72
b1111000000000001 #
b1111100000000000 &
#73
#74
b1111111111111111 #
b1110 %
b0000000000000001 &
#75
#76
b0000100000000000 #
b1111100000000000 &
#77
#78
b1111000011110001 #
b0000111100001111 &
#79
#80
b0000000000000000 #
b1111 %
b0000000000000000 &
#81
#82
b1010101111001101 #
